crestdsl/__init__.py
crestdsl/caching.py
crestdsl/config.py
crestdsl/sourcehelper.py
crestdsl/ml/__init__.py
crestdsl/ml/decorators.py
crestdsl/ml/functionlearn.py
crestdsl/ml/learners.py
crestdsl/model/__init__.py
crestdsl/model/datatypes.py
crestdsl/model/decorators.py
crestdsl/model/entity.py
crestdsl/model/meta.py
crestdsl/model/model.py
crestdsl/model/ports.py
crestdsl/model/resource.py
crestdsl/model/systemcheck.py
crestdsl/model/api/__init__.py
crestdsl/model/api/api.py
crestdsl/model/api/convenienceAPI.py
crestdsl/planning/__init__.py
crestdsl/simulation/__init__.py
crestdsl/simulation/basesimulator.py
crestdsl/simulation/conditiontimedchangecalculator.py
crestdsl/simulation/contextconditiontimedchangecalculator.py
crestdsl/simulation/dependencyOrder.py
crestdsl/simulation/epsilon.py
crestdsl/simulation/fastconditiontimedchangecalculator.py
crestdsl/simulation/interactivesimulator.py
crestdsl/simulation/plansimulator.py
crestdsl/simulation/simulator.py
crestdsl/simulation/to_z3.py
crestdsl/simulation/tracestore.py
crestdsl/simulation/transitiontime.py
crestdsl/simulation/z3calculator.py
crestdsl/simulation/z3conditionchangecalculator.py
crestdsl/simulation/z3simulator.py
crestdsl/ui/__init__.py
crestdsl/ui/dotter.py
crestdsl/ui/draw_statespace.py
crestdsl/ui/elk.py
crestdsl/ui/index.html
crestdsl/ui/index.js
crestdsl/ui/index_with_comments.html
crestdsl/ui/statespace.html
crestdsl/verification/__init__.py
crestdsl/verification/alpha_beta.py
crestdsl/verification/checklib.py
crestdsl/verification/continuous.py
crestdsl/verification/modelchecker.py
crestdsl/verification/modelchecking.py
crestdsl/verification/normalform.py
crestdsl/verification/pointwise.py
crestdsl/verification/reachabilitycalculator.py
crestdsl/verification/simplify.py
crestdsl/verification/small_normalform.py
crestdsl/verification/statespace.py
crestdsl/verification/tctl.py
crestdsl/verification/verifier.py
tests/__init__.py
tests/model/__init__.py
tests/model/test_entity_creation.py
crestdsl-0.5.2.dist-info/LICENSE.md
crestdsl-0.5.2.dist-info/METADATA
crestdsl-0.5.2.dist-info/WHEEL
crestdsl-0.5.2.dist-info/top_level.txt
crestdsl-0.5.2.dist-info/RECORD
