Metadata-Version: 2.1
Name: crestdsl
Version: 0.5.2
Summary: A Continuous REactive SysTems DSL
Home-page: https://github.com/crestdsl/CREST
Author: Stefan Klikovits
Author-email: crestdsl@klikovits.net
License: UNKNOWN
Platform: UNKNOWN
Classifier: Programming Language :: Python :: 3
Classifier: License :: OSI Approved :: MIT License
Classifier: Operating System :: OS Independent
Requires-Dist: importlib-resources
Requires-Dist: colored (>=1.3)
Requires-Dist: methoddispatch (>=2)
Requires-Dist: matplotlib
Requires-Dist: graphviz
Requires-Dist: pygraphviz (>=1.5)
Requires-Dist: astor (>=0.7)
Requires-Dist: pandas (>0.1)
Requires-Dist: numpy
Requires-Dist: networkx (>=2.2)
Requires-Dist: plotly (>=3.5)
Requires-Dist: cufflinks (>=0.14)
Requires-Dist: pwlf (>=0.3)
Requires-Dist: importnb
Requires-Dist: sklearn
